{
  "Title": "BucketAuto",
  "DefaultValues": {},
  "Fields": [
    {
      "name": "groupBy",
      "label": "Group By Expression",
      "tooltip": "Group by expression",
      "type": "Combo",
      "lookup": "dbkodaListAttributesAgg",
      "lookup_arguments": [
        {
          "name": "prevAttributes",
          "value": "prevAttributes"
        }
      ]
    },
    {
      "name": "buckets",
      "label": "Buckets",
      "tooltip": "Number of buckets",
      "type": "Numeric"
    },
    {
      "name": "granularity",
      "label": "Granularity",
      "tooltip": "Granularity string (see lookup)",
      "type": "Combo",
      "lookup": "dbkodaGranularityLookup",
      "lookup_arguments": [
        {
          "name": "db",
          "value": "database"
        }
      ]
    },
    {
      "name": "AggregateKeys",
      "label": "Columns To Aggregate",
      "type": "Table",
      "columns": [
        {
          "name": "AttributeName",
          "label": "Attribute",
          "tooltip": "Name of the attribute to be filtered",
          "type": "Combo",
          "lookup": "dbkodaListAttributesAgg",
          "lookup_arguments": [
            {
              "name": "prevAttributes",
              "value": "prevAttributes"
            }
          ]
        },
        {
          "name": "Aggregation",
          "Label": "Aggregation",
          "type": "Combo",
          "tooltip": "Aggregation Operation",
          "lookup": "dbkodaAggOperators",
          "lookup_arguments": [
            {
              "name": "db",
              "value": "database"
            }
          ]
        }
      ]
    }
  ]
}
